admin_wizard/__init__.py
admin_wizard/admin.py
admin_wizard/forms.py
admin_wizard/models.py
admin_wizard/tests.py
admin_wizard/templates/admin/admin_action_wizard.html
admin_wizard/templates/admin/admin_update_wizard.html
django_admin_wizard-0.6.0.dist-info/licenses/LICENSE
django_admin_wizard-0.6.0.dist-info/METADATA
django_admin_wizard-0.6.0.dist-info/WHEEL
django_admin_wizard-0.6.0.dist-info/top_level.txt
django_admin_wizard-0.6.0.dist-info/RECORD
